{
  "events": [
    {
      "date": "2026-02-07",
      "time": "21:30",
      "event": "CPI (Consumer Price Index)",
      "impact": "High",
      "forecast": "3.1%",
      "previous": "3.2%"
    },
    {
      "date": "2026-02-08",
      "time": "03:00",
      "event": "FOMC Meeting Minutes",
      "impact": "High",
      "forecast": "-",
      "previous": "-"
    },
    {
      "date": "2026-02-09",
      "time": "21:30",
      "event": "Non-Farm Payrolls",
      "impact": "High",
      "forecast": "180K",
      "previous": "216K"
    }
  ]
}