{
    "date": "2026-02-27 08:23:04 KST",
    "market_indices": {
        "KOSPI": {
            "symbol": "KS11",
            "name": "코스피",
            "price": "6,244.13",
            "change": "-1.00%"
        },
        "KOSDAQ": {
            "symbol": "KQ11",
            "name": "코스닥",
            "price": "1,192.78",
            "change": "+0.39%"
        },
        "KOSPI200": {
            "symbol": "KS200",
            "name": "코스피 200",
            "price": "933.34",
            "change": "-1.13%"
        }
    },
    "commodities": [
        {
            "name": "원/달러 환율",
            "price": "1,438.61",
            "change": "+0.82%"
        },
        {
            "name": "WTI 원유",
            "price": "65.84",
            "change": "+0.97%"
        },
        {
            "name": "국제 금",
            "price": "5,195.90",
            "change": "+0.37%"
        }
    ],
    "sector_heatmap": [
        {
            "sector": "철강/금속",
            "change": 6.025,
            "change_str": "+6.03%",
            "stocks": [
                {
                    "symbol": "005490",
                    "name": "POSCO홀딩스",
                    "change": "+1.35%"
                },
                {
                    "symbol": "004020",
                    "name": "현대제철",
                    "change": "+19.85%"
                },
                {
                    "symbol": "010130",
                    "name": "고려아연",
                    "change": "-1.22%"
                }
            ]
        },
        {
            "sector": "자동차",
            "change": 4.507499999999999,
            "change_str": "+4.51%",
            "stocks": [
                {
                    "symbol": "005380",
                    "name": "현대차",
                    "change": "+10.67%"
                },
                {
                    "symbol": "000270",
                    "name": "기아",
                    "change": "-0.24%"
                },
                {
                    "symbol": "012330",
                    "name": "현대모비스",
                    "change": "-2.27%"
                }
            ]
        },
        {
            "sector": "반도체",
            "change": 3.2980000000000005,
            "change_str": "+3.30%",
            "stocks": [
                {
                    "symbol": "005930",
                    "name": "삼성전자",
                    "change": "-0.69%"
                },
                {
                    "symbol": "000660",
                    "name": "SK하이닉스",
                    "change": "-3.46%"
                },
                {
                    "symbol": "042700",
                    "name": "한미반도체",
                    "change": "+17.42%"
                }
            ]
        },
        {
            "sector": "2차전지",
            "change": 1.335,
            "change_str": "+1.33%",
            "stocks": [
                {
                    "symbol": "373220",
                    "name": "LG에너지솔루션",
                    "change": "+0.00%"
                },
                {
                    "symbol": "006400",
                    "name": "삼성SDI",
                    "change": "+3.79%"
                },
                {
                    "symbol": "247540",
                    "name": "에코프로비엠",
                    "change": "+0.91%"
                }
            ]
        },
        {
            "sector": "조선/중공업",
            "change": 0.7633333333333333,
            "change_str": "+0.76%",
            "stocks": [
                {
                    "symbol": "329180",
                    "name": "HD현대중공업",
                    "change": "+1.86%"
                },
                {
                    "symbol": "010140",
                    "name": "삼성중공업",
                    "change": "+0.87%"
                },
                {
                    "symbol": "009540",
                    "name": "HD한국조선해양",
                    "change": "-0.44%"
                }
            ]
        },
        {
            "sector": "화학/에너지",
            "change": 0.5075,
            "change_str": "+0.51%",
            "stocks": [
                {
                    "symbol": "051910",
                    "name": "LG화학",
                    "change": "+7.05%"
                },
                {
                    "symbol": "096770",
                    "name": "SK이노베이션",
                    "change": "-1.77%"
                },
                {
                    "symbol": "010950",
                    "name": "S-Oil",
                    "change": "-3.25%"
                }
            ]
        },
        {
            "sector": "IT/플랫폼",
            "change": -0.21999999999999997,
            "change_str": "-0.22%",
            "stocks": [
                {
                    "symbol": "035420",
                    "name": "NAVER",
                    "change": "-2.30%"
                },
                {
                    "symbol": "035720",
                    "name": "카카오",
                    "change": "+1.47%"
                },
                {
                    "symbol": "035810",
                    "name": "이지홀딩스",
                    "change": "-1.10%"
                }
            ]
        },
        {
            "sector": "게임/엔터",
            "change": -0.33199999999999996,
            "change_str": "-0.33%",
            "stocks": [
                {
                    "symbol": "036570",
                    "name": "엔씨소프트",
                    "change": "-0.22%"
                },
                {
                    "symbol": "259960",
                    "name": "크래프톤",
                    "change": "-2.17%"
                },
                {
                    "symbol": "352820",
                    "name": "하이브",
                    "change": "-0.90%"
                }
            ]
        },
        {
            "sector": "바이오",
            "change": -1.16,
            "change_str": "-1.16%",
            "stocks": [
                {
                    "symbol": "207940",
                    "name": "삼성바이오로직스",
                    "change": "+0.68%"
                },
                {
                    "symbol": "068270",
                    "name": "셀트리온",
                    "change": "-1.45%"
                },
                {
                    "symbol": "000100",
                    "name": "유한양행",
                    "change": "-0.63%"
                }
            ]
        },
        {
            "sector": "금융/지주",
            "change": -2.492,
            "change_str": "-2.49%",
            "stocks": [
                {
                    "symbol": "105560",
                    "name": "KB금융",
                    "change": "-3.81%"
                },
                {
                    "symbol": "055550",
                    "name": "신한지주",
                    "change": "-3.00%"
                },
                {
                    "symbol": "086790",
                    "name": "하나금융지주",
                    "change": "-2.48%"
                }
            ]
        }
    ],
    "ipo_news": [
        {
            "name": "IPO/증자 정보 업데이트 중",
            "status": "알림",
            "manager": "-",
            "price": "-",
            "date": "-"
        }
    ],
    "market_news": [
        {
            "title": "국민연금 '231조' 대박 터졌다…역대급 수익 낸 비결은?",
            "url": "https://news.google.com/rss/articles/CBMiT0FVX3lxTFBtSkxoTFRlNmk5ZVI0c1NOZGFNY3NNR1o4SVUwQkxhQjB3UW5iNzRqZzRCcEJSdVpyTVpXMVhVQ3Rrb29TRXVCajN6c3g2TUE?oc=5",
            "source": "v.daum.net",
            "date": "Fri, 27 Feb 2026 01:04:37 GMT"
        },
        {
            "title": "[특징주] 현대차, 새만금 투자 소식에 9% 강세",
            "url": "https://news.google.com/rss/articles/CBMibEFVX3lxTE9YNWVfbXY1MWRta0FIOVJ4RUZQc3ZrZXdpMlYtOG9GX2dxSk1Ta0ZScEE3Z3dkT0trYVhWS2hCZ1pic2dnU00wSnB4dk9HTmhuQWxjZkFpTWNLZjhvTEJxcXFiM2syQ0VraXdGYdIBcEFVX3lxTE5zYkVyRThzT1ZwbEpEV29YZklEV05jRV9KV1RIUDh4amNyTjVTYUIwY3pZM0VjMXc5cXp4bVVqdGNnUy11YmJ0aG43Mkx0SHRQRjVZR1hDdGhtaUxPT2pydnNCRmQ5azd4bkExc1RmTks?oc=5",
            "source": "ceodaily.co.kr",
            "date": "Fri, 27 Feb 2026 04:56:08 GMT"
        },
        {
            "title": "달아오르는 코스피…국내증시 9황제 시대 개막",
            "url": "https://news.google.com/rss/articles/CBMiaEFVX3lxTFB4TWJScXFYQ0c1WV81WlpDRC1BTXo1eHBoRmxiWDlMeF83ZENCUG5BZWF6a2hGLVAwWDAtUHJuVHJTblJ5Ymg0UldSWUFVZzMzSEtYZHd4V29iaG9kYXZIc2pWU1drS28z?oc=5",
            "source": "mt.co.kr",
            "date": "Wed, 25 Feb 2026 06:50:02 GMT"
        },
        {
            "title": "“진짜 강심장이네” 코스피 3배 레버리지 사려고 줄 섰다…99%나 급등 [투자360]",
            "url": "https://news.google.com/rss/articles/CBMiT0FVX3lxTE5MUkY4bWtOSUhpZEVyOUM5TTdTaG41NHJ2NjN3TVBXU3BJaXVJdlNJN08zYTN2dWNXTVpOaDZ3allNNjl4blVHWmMxLWFIRjA?oc=5",
            "source": "v.daum.net",
            "date": "Fri, 27 Feb 2026 04:41:44 GMT"
        },
        {
            "title": "\"지금 투자하면 패가망신 지름길\" 증시 퇴출 고위험 종목 14개",
            "url": "https://news.google.com/rss/articles/CBMiT0FVX3lxTFBYbGJhVWlvNFdoUy1UOW5DaEl2ZkZrMHlOc2RsMUVQWGQwaTlWWjFoYmJPejVKOU5BanRaUHhXZlcxUFBiRk91amJtbjZjRHM?oc=5",
            "source": "v.daum.net",
            "date": "Thu, 26 Feb 2026 23:21:26 GMT"
        },
        {
            "title": "[굿모닝 증시]美 반도체주 약세에…韓 증시 하락출발 전망",
            "url": "https://news.google.com/rss/articles/CBMiT0FVX3lxTE1VRTR2d2JZZlM0azJ5RlBKM25OcV9FV1ZSODUxalVXX1R5b1Rud1lkWDVhNG1KN3VocFhFTEx5Vlc1X3l4UTFOZ2l4WG5GcHM?oc=5",
            "source": "v.daum.net",
            "date": "Thu, 26 Feb 2026 23:28:15 GMT"
        },
        {
            "title": "코스피, 외인 5조원대 투매에도 상승 전환…최고치 경신",
            "url": "https://news.google.com/rss/articles/CBMiT0FVX3lxTE9fU1Z2dExHcXdueHBtdTF4LTdpeDBzV3FpSWpZeXlqUGJPTnJBaFpSZEJFVGwyTFNNb2tKS3RNVUxKQloweGc5SDhrd2NIOVk?oc=5",
            "source": "v.daum.net",
            "date": "Fri, 27 Feb 2026 05:39:42 GMT"
        },
        {
            "title": "“이왕 주식할거면 절세혜택도 챙겨야”…ISA가입 한달새 42만명 급증",
            "url": "https://news.google.com/rss/articles/CBMiT0FVX3lxTE1OQWdtMTYyNVRxbUVobnlxVU5TMThuVjhRbV9kNGZzSzg4d29ZRkNZaU9wYWRjYWY5a0RieW91Q2wzdXBBSFoxVDV4S1U2bUU?oc=5",
            "source": "v.daum.net",
            "date": "Thu, 26 Feb 2026 21:36:00 GMT"
        },
        {
            "title": "2월 15조 매수세 ‘기관’…삼전 4조, SK하이닉스 2조 사들였다",
            "url": "https://news.google.com/rss/articles/CBMiT0FVX3lxTE5aNF9GQ0RzSTRzSFVzWU1xNnpaV3lQeEpnYXJLTnlLOVk3TnRac1JlNDdWY2dBWFd3YXM4bHpHSkhzMjNsRjNsZ0dqdGJVejA?oc=5",
            "source": "v.daum.net",
            "date": "Fri, 27 Feb 2026 07:09:44 GMT"
        },
        {
            "title": "‘증시 활황’에 ISA 가입자 800만명…가입금액 50兆 돌파",
            "url": "https://news.google.com/rss/articles/CBMiRkFVX3lxTFBHMXBLLXU3WTMwNHp1WUNUb1FOSmFtR0hCd0l6ZmVGd1V3LXVfRDRLN09MTE9TZUZpdUpFVDZOeEgyWlMzNUE?oc=5",
            "source": "v.daum.net",
            "date": "Thu, 26 Feb 2026 02:12:44 GMT"
        }
    ],
    "investor_flows": {
        "KOSPI": [
            {
                "label": "개인",
                "value": "+63099억",
                "status": "매수"
            },
            {
                "label": "외국인",
                "value": "-71153억",
                "status": "매도"
            },
            {
                "label": "기관",
                "value": "+5459억",
                "status": "매수"
            }
        ],
        "KOSDAQ": [
            {
                "label": "개인",
                "value": "-4708억",
                "status": "매도"
            },
            {
                "label": "외국인",
                "value": "+636억",
                "status": "매수"
            },
            {
                "label": "기관",
                "value": "+4446억",
                "status": "매수"
            }
        ]
    },
    "top_stocks": [
        {
            "symbol": "322000",
            "name": "HD현대에너지솔루션",
            "price": "104,000",
            "change": "+30.00",
            "volume": "5,515,398",
            "market": "KOSPI"
        },
        {
            "symbol": "054620",
            "name": "APS",
            "price": "6,500",
            "change": "+30.00",
            "volume": "1,095,511",
            "market": "KOSDAQ"
        },
        {
            "symbol": "027360",
            "name": "아주IB투자",
            "price": "5,810",
            "change": "+29.98",
            "volume": "26,652,919",
            "market": "KOSDAQ"
        },
        {
            "symbol": "001510",
            "name": "SK증권",
            "price": "2,125",
            "change": "-1.16",
            "volume": "131,671,926",
            "market": "KOSPI"
        },
        {
            "symbol": "011930",
            "name": "신성이엔지",
            "price": "2,450",
            "change": "+14.75",
            "volume": "83,980,134",
            "market": "KOSPI"
        },
        {
            "symbol": "004060",
            "name": "SG세계물산",
            "price": "685",
            "change": "+3.32",
            "volume": "69,501,704",
            "market": "KOSPI"
        },
        {
            "symbol": "005930",
            "name": "삼성전자",
            "price": "216,500",
            "change": "-0.69",
            "volume": "51,774,768",
            "market": "KOSPI"
        },
        {
            "symbol": "000660",
            "name": "SK하이닉스",
            "price": "1,061,000",
            "change": "-3.46",
            "volume": "6,453,062",
            "market": "KOSPI"
        },
        {
            "symbol": "086520",
            "name": "에코프로",
            "price": "185,000",
            "change": "+0.43",
            "volume": "2,792,329",
            "market": "KOSDAQ GLOBAL"
        },
        {
            "symbol": "196170",
            "name": "알테오젠",
            "price": "407,500",
            "change": "+1.12",
            "volume": "437,970",
            "market": "KOSDAQ GLOBAL"
        }
    ],
    "leaders_kospi": [
        {
            "symbol": "005930",
            "name": "삼성전자",
            "price": "216,500",
            "change": "-0.69",
            "volume": "51,774,768",
            "market": "KOSPI"
        },
        {
            "symbol": "000660",
            "name": "SK하이닉스",
            "price": "1,061,000",
            "change": "-3.46",
            "volume": "6,453,062",
            "market": "KOSPI"
        },
        {
            "symbol": "005380",
            "name": "현대차",
            "price": "674,000",
            "change": "+10.67",
            "volume": "4,354,409",
            "market": "KOSPI"
        },
        {
            "symbol": "005935",
            "name": "삼성전자우",
            "price": "143,800",
            "change": "-3.30",
            "volume": "9,957,791",
            "market": "KOSPI"
        },
        {
            "symbol": "373220",
            "name": "LG에너지솔루션",
            "price": "427,000",
            "change": "+0.00",
            "volume": "591,387",
            "market": "KOSPI"
        },
        {
            "symbol": "402340",
            "name": "SK스퀘어",
            "price": "645,000",
            "change": "-5.01",
            "volume": "1,032,548",
            "market": "KOSPI"
        },
        {
            "symbol": "207940",
            "name": "삼성바이오로직스",
            "price": "1,778,000",
            "change": "+0.68",
            "volume": "97,725",
            "market": "KOSPI"
        },
        {
            "symbol": "000270",
            "name": "기아",
            "price": "205,500",
            "change": "-0.24",
            "volume": "2,945,241",
            "market": "KOSPI"
        },
        {
            "symbol": "034020",
            "name": "두산에너빌리티",
            "price": "106,300",
            "change": "+2.41",
            "volume": "8,296,804",
            "market": "KOSPI"
        },
        {
            "symbol": "329180",
            "name": "HD현대중공업",
            "price": "603,000",
            "change": "+1.86",
            "volume": "424,522",
            "market": "KOSPI"
        }
    ],
    "leaders_kosdaq": [
        {
            "symbol": "086520",
            "name": "에코프로",
            "price": "185,000",
            "change": "+0.43",
            "volume": "2,792,329",
            "market": "KOSDAQ GLOBAL"
        },
        {
            "symbol": "196170",
            "name": "알테오젠",
            "price": "407,500",
            "change": "+1.12",
            "volume": "437,970",
            "market": "KOSDAQ GLOBAL"
        },
        {
            "symbol": "247540",
            "name": "에코프로비엠",
            "price": "221,500",
            "change": "+0.91",
            "volume": "786,277",
            "market": "KOSDAQ GLOBAL"
        },
        {
            "symbol": "000250",
            "name": "삼천당제약",
            "price": "825,000",
            "change": "+8.98",
            "volume": "501,731",
            "market": "KOSDAQ"
        },
        {
            "symbol": "277810",
            "name": "레인보우로보틱스",
            "price": "860,000",
            "change": "-2.27",
            "volume": "194,359",
            "market": "KOSDAQ"
        },
        {
            "symbol": "298380",
            "name": "에이비엘바이오",
            "price": "194,000",
            "change": "+1.52",
            "volume": "591,852",
            "market": "KOSDAQ"
        },
        {
            "symbol": "950160",
            "name": "코오롱티슈진",
            "price": "107,000",
            "change": "+1.90",
            "volume": "590,057",
            "market": "KOSDAQ"
        },
        {
            "symbol": "058470",
            "name": "리노공업",
            "price": "106,200",
            "change": "-0.56",
            "volume": "1,334,311",
            "market": "KOSDAQ GLOBAL"
        },
        {
            "symbol": "214370",
            "name": "케어젠",
            "price": "136,800",
            "change": "-2.01",
            "volume": "122,690",
            "market": "KOSDAQ"
        },
        {
            "symbol": "141080",
            "name": "리가켐바이오",
            "price": "191,700",
            "change": "+2.35",
            "volume": "360,988",
            "market": "KOSDAQ GLOBAL"
        }
    ],
    "gainers": [
        {
            "symbol": "322000",
            "name": "HD현대에너지솔루션",
            "price": "104,000",
            "change": "+30.00",
            "volume": "5,515,398",
            "market": "KOSPI"
        },
        {
            "symbol": "054620",
            "name": "APS",
            "price": "6,500",
            "change": "+30.00",
            "volume": "1,095,511",
            "market": "KOSDAQ"
        },
        {
            "symbol": "027360",
            "name": "아주IB투자",
            "price": "5,810",
            "change": "+29.98",
            "volume": "26,652,919",
            "market": "KOSDAQ"
        },
        {
            "symbol": "089230",
            "name": "THE E&M",
            "price": "1,462",
            "change": "+29.96",
            "volume": "3,148,540",
            "market": "KOSDAQ"
        },
        {
            "symbol": "307750",
            "name": "국전약품",
            "price": "4,145",
            "change": "+29.94",
            "volume": "7,720,978",
            "market": "KOSDAQ"
        },
        {
            "symbol": "043150",
            "name": "바텍",
            "price": "27,350",
            "change": "+29.93",
            "volume": "138,816",
            "market": "KOSDAQ"
        },
        {
            "symbol": "229000",
            "name": "젠큐릭스",
            "price": "5,860",
            "change": "+29.93",
            "volume": "17,890,218",
            "market": "KOSDAQ"
        },
        {
            "symbol": "006920",
            "name": "모헨즈",
            "price": "4,625",
            "change": "+29.92",
            "volume": "6,840,486",
            "market": "KOSDAQ"
        },
        {
            "symbol": "061040",
            "name": "알에프텍",
            "price": "2,365",
            "change": "+29.87",
            "volume": "970,894",
            "market": "KOSDAQ"
        },
        {
            "symbol": "001020",
            "name": "페이퍼코리아",
            "price": "849",
            "change": "+25.22",
            "volume": "15,012,271",
            "market": "KOSPI"
        }
    ],
    "volume": [
        {
            "symbol": "001510",
            "name": "SK증권",
            "price": "2,125",
            "change": "-1.16",
            "volume": "131,671,926",
            "market": "KOSPI"
        },
        {
            "symbol": "011930",
            "name": "신성이엔지",
            "price": "2,450",
            "change": "+14.75",
            "volume": "83,980,134",
            "market": "KOSPI"
        },
        {
            "symbol": "004060",
            "name": "SG세계물산",
            "price": "685",
            "change": "+3.32",
            "volume": "69,501,704",
            "market": "KOSPI"
        },
        {
            "symbol": "005930",
            "name": "삼성전자",
            "price": "216,500",
            "change": "-0.69",
            "volume": "51,774,768",
            "market": "KOSPI"
        },
        {
            "symbol": "006340",
            "name": "대원전선",
            "price": "6,790",
            "change": "+5.93",
            "volume": "47,823,910",
            "market": "KOSPI"
        },
        {
            "symbol": "038500",
            "name": "삼표시멘트",
            "price": "17,350",
            "change": "+13.62",
            "volume": "44,896,791",
            "market": "KOSDAQ"
        },
        {
            "symbol": "001290",
            "name": "상상인증권",
            "price": "1,500",
            "change": "-3.72",
            "volume": "40,170,541",
            "market": "KOSPI"
        },
        {
            "symbol": "900300",
            "name": "오가닉티코스메틱",
            "price": "128",
            "change": "+3.23",
            "volume": "37,634,814",
            "market": "KOSDAQ"
        },
        {
            "symbol": "227950",
            "name": "엔투텍",
            "price": "569",
            "change": "-5.32",
            "volume": "37,295,234",
            "market": "KOSDAQ"
        },
        {
            "symbol": "187660",
            "name": "현대ADM",
            "price": "18,670",
            "change": "+0.00",
            "volume": "33,198,163",
            "market": "KOSDAQ"
        }
    ],
    "ai_analysis": {
        "005930": {
            "insight": "메모리 반도체 업황 회복과 파운드리 성장 잠재력으로 장기적인 투자 가치가 높음.",
            "risk": "글로벌 경기 침체 심화 및 경쟁 심화에 따른 수익성 악화 가능성이 존재함.",
            "swot_s": "브랜드 인지도, 기술 리더십, 압도적인 시장 점유율, 풍부한 현금 보유량",
            "swot_w": "반도체 산업 의존도 심화, 복잡한 지배구조, 경기 변동에 민감",
            "swot_o": "AI, 5G, 전장 등 미래 성장 산업 확대, 정부의 반도체 산업 지원 정책",
            "swot_t": "글로벌 경기 침체, 미중 무역 갈등, 경쟁 심화 (TSMC 등)",
            "upside": "+20%",
            "dcf_target": "95000",
            "dcf_bear": "75000",
            "dcf_bull": "110000"
        },
        "000660": {
            "insight": "DRAM 시장 회복과 HBM 수요 증가로 실적 개선이 기대됨.",
            "risk": "반도체 업황 변동성 및 경쟁 심화로 인한 수익성 악화 가능성이 존재함.",
            "swot_s": "고대역폭 메모리(HBM) 기술력, DRAM 시장 점유율, SK그룹의 지원",
            "swot_w": "삼성전자에 비해 낮은 브랜드 인지도, 메모리 반도체 의존도",
            "swot_o": "AI 시대에 따른 HBM 수요 급증, 정부의 반도체 산업 지원 정책",
            "swot_t": "글로벌 경기 침체, 미중 무역 갈등, 경쟁 심화 (삼성전자, 마이크론)",
            "upside": "+25%",
            "dcf_target": "200000",
            "dcf_bear": "150000",
            "dcf_bull": "230000"
        },
        "005380": {
            "insight": "전기차 시장 성장과 고급 브랜드 제네시스 판매 호조로 실적 개선이 지속될 전망.",
            "risk": "글로벌 경기 침체 및 경쟁 심화에 따른 판매 부진 가능성이 존재함.",
            "swot_s": "글로벌 자동차 시장 점유율, 전기차 기술력, 제네시스 브랜드 성공",
            "swot_w": "노조 리스크, 내연기관차 중심의 사업 구조, 중국 시장 부진",
            "swot_o": "전기차 시장 성장, 친환경차 규제 강화, 정부의 친환경차 지원 정책",
            "swot_t": "글로벌 경기 침체, 경쟁 심화 (테슬라 등), 원자재 가격 상승",
            "upside": "+15%",
            "dcf_target": "300000",
            "dcf_bear": "220000",
            "dcf_bull": "350000"
        },
        "005935": {
            "insight": "삼성전자와 동일한 사업 포트폴리오를 가지며 상대적으로 저렴한 가격으로 투자 매력이 있음.",
            "risk": "의결권이 없는 우선주 특성상 주가 변동성이 높을 수 있음.",
            "swot_s": "삼성전자와 동일한 사업 영위, 낮은 가격, 안정적인 배당 수익",
            "swot_w": "의결권 없음, 낮은 유동성",
            "swot_o": "삼성전자 실적 개선, 배당 확대 정책",
            "swot_t": "삼성전자 주가 하락, 투자 심리 악화",
            "upside": "+12%",
            "dcf_target": "85000",
            "dcf_bear": "68000",
            "dcf_bull": "98000"
        },
        "373220": {
            "insight": "글로벌 배터리 시장 성장과 GM 등 주요 고객사와의 협력 확대로 장기적인 성장 동력을 확보함.",
            "risk": "경쟁 심화 및 원자재 가격 변동에 따른 수익성 악화 가능성이 존재함.",
            "swot_s": "글로벌 배터리 시장 점유율, 기술 경쟁력, LG그룹의 지원",
            "swot_w": "높은 투자 비용, 특정 고객사 의존도, 경쟁사 대비 낮은 수익성",
            "swot_o": "전기차 시장 성장, 에너지 저장 시스템(ESS) 시장 확대, 정부의 친환경 에너지 정책",
            "swot_t": "경쟁 심화 (CATL 등), 원자재 가격 상승, 기술 유출 위험",
            "upside": "+18%",
            "dcf_target": "650000",
            "dcf_bear": "480000",
            "dcf_bull": "750000"
        },
        "402340": {
            "insight": "SK그룹의 투자형 지주회사로, 다양한 신성장 사업 투자에 따른 잠재적 가치 상승 기대.",
            "risk": "투자 성과 불확실성 및 지주회사 할인율 적용으로 주가 변동성이 높을 수 있음.",
            "swot_s": "SK그룹의 강력한 지원, 다양한 투자 포트폴리오, 성장 잠재력",
            "swot_w": "투자 성과 불확실성, 지주회사 할인율, 복잡한 지배구조",
            "swot_o": "신성장 산업 투자 확대 (AI, 바이오 등), 정부의 투자 활성화 정책",
            "swot_t": "글로벌 경기 침체, 투자 실패 위험, 규제 강화",
            "upside": "+10%",
            "dcf_target": "120000",
            "dcf_bear": "90000",
            "dcf_bull": "135000"
        },
        "207940": {
            "insight": "바이오 의약품 위탁생산(CMO) 시장 성장과 생산능력 확대로 지속적인 성장 기대.",
            "risk": "경쟁 심화 및 생산 차질 발생 가능성이 존재함.",
            "swot_s": "압도적인 생산능력, 우수한 품질 관리, 삼성그룹의 지원",
            "swot_w": "CMO 사업 의존도, 높은 설비 투자 비용",
            "swot_o": "바이오 의약품 시장 성장, 아웃소싱 확대 추세, 정부의 바이오 산업 육성 정책",
            "swot_t": "경쟁 심화 (론자 등), 생산 차질 위험, 규제 강화",
            "upside": "+17%",
            "dcf_target": "900000",
            "dcf_bear": "700000",
            "dcf_bull": "1000000"
        },
        "000270": {
            "insight": "전기차 라인업 강화와 브랜드 이미지 개선으로 현대차와 함께 성장할 것으로 기대.",
            "risk": "글로벌 경기 침체 및 경쟁 심화에 따른 판매 부진 가능성이 존재함.",
            "swot_s": "글로벌 자동차 시장 점유율, 디자인 경쟁력, 전기차 전환 노력",
            "swot_w": "노조 리스크, 브랜드 이미지 개선 필요, 내연기관차 중심의 사업 구조",
            "swot_o": "전기차 시장 성장, 친환경차 규제 강화, 정부의 친환경차 지원 정책",
            "swot_t": "글로벌 경기 침체, 경쟁 심화 (테슬라 등), 원자재 가격 상승",
            "upside": "+16%",
            "dcf_target": "120000",
            "dcf_bear": "90000",
            "dcf_bull": "135000"
        },
        "034020": {
            "insight": "원자력 발전 및 수소 에너지 사업 확대로 친환경 에너지 기업으로의 전환을 추진 중.",
            "risk": "정책 변화 및 경쟁 심화에 따른 사업 불확실성이 존재함.",
            "swot_s": "원자력 발전 기술력, 에너지 사업 경험, 정부의 에너지 정책 지원",
            "swot_w": "높은 부채 비율, 원자력 발전 안전성 논란, 정책 변화에 민감",
            "swot_o": "친환경 에너지 수요 증가, 정부의 탈탄소 정책, 원자력 발전 재평가",
            "swot_t": "정책 변화, 경쟁 심화 (신재생 에너지 기업), 원자력 발전 안전 문제",
            "upside": "+20%",
            "dcf_target": "25000",
            "dcf_bear": "18000",
            "dcf_bull": "30000"
        },
        "329180": {
            "insight": "조선업 업황 회복과 친환경 선박 수주 증가로 실적 개선이 기대됨.",
            "risk": "원자재 가격 변동 및 인건비 상승에 따른 수익성 악화 가능성이 존재함.",
            "swot_s": "글로벌 조선 시장 점유율, 친환경 선박 기술력, 현대중공업 그룹의 지원",
            "swot_w": "높은 부채 비율, 수주 변동성, 인건비 상승",
            "swot_o": "글로벌 경기 회복, 친환경 선박 수요 증가, 정부의 조선 산업 지원 정책",
            "swot_t": "글로벌 경기 침체, 원자재 가격 상승, 경쟁 심화 (중국 조선사)",
            "upside": "+18%",
            "dcf_target": "180000",
            "dcf_bear": "140000",
            "dcf_bull": "200000"
        },
        "086520": {
            "insight": "2차전지 양극재 시장 성장과 함께 지속적인 성장세를 이어갈 것으로 예상되나, 높은 밸류에이션에 대한 부담 존재.",
            "risk": "리튬 가격 변동 및 경쟁 심화에 따른 수익성 악화 가능성이 존재함.",
            "swot_s": "양극재 기술력, 높은 성장률, 2차전지 시장의 성장",
            "swot_w": "높은 밸류에이션, 리튬 가격 변동에 민감, 특정 고객사 의존도",
            "swot_o": "전기차 시장 성장, 에너지 저장 시스템(ESS) 시장 확대, 정부의 친환경 에너지 정책",
            "swot_t": "경쟁 심화 (POSCO홀딩스 등), 리튬 가격 하락, 기술 변화에 대한 대응",
            "upside": "+10%",
            "dcf_target": "800000",
            "dcf_bear": "650000",
            "dcf_bull": "900000"
        },
        "196170": {
            "insight": "SC제형 기술 기반의 플랫폼 확장 및 글로벌 제약사와의 협력 확대로 성장 잠재력 높음.",
            "risk": "임상 시험 실패 및 경쟁 심화에 따른 사업 불확실성이 존재함.",
            "swot_s": "SC제형 플랫폼 기술, 글로벌 제약사와의 협력, 높은 성장 잠재력",
            "swot_w": "임상 시험 성공 불확실성, 경쟁 심화, 기술 의존도",
            "swot_o": "글로벌 바이오 의약품 시장 성장, 플랫폼 기술 수요 증가, 정부의 바이오 산업 육성 정책",
            "swot_t": "임상 시험 실패 위험, 경쟁 심화, 규제 강화",
            "upside": "+25%",
            "dcf_target": "150000",
            "dcf_bear": "100000",
            "dcf_bull": "180000"
        },
        "247540": {
            "insight": "전기차 시장 확대에 따른 양극재 수요 증가로 꾸준한 실적 성장이 기대되지만, 원재료 가격 변동에 주의 필요.",
            "risk": "원자재 가격 변동 및 경쟁 심화에 따른 수익성 악화 가능성이 존재함.",
            "swot_s": "양극재 생산능력, 기술 경쟁력, 안정적인 고객 기반",
            "swot_w": "원재료 가격 변동에 민감, 특정 고객사 의존도, 경쟁 심화",
            "swot_o": "전기차 시장 성장, 에너지 저장 시스템(ESS) 시장 확대, 정부의 친환경 에너지 정책",
            "swot_t": "경쟁 심화 (엘앤에프 등), 원자재 가격 하락, 기술 변화에 대한 대응",
            "upside": "+12%",
            "dcf_target": "350000",
            "dcf_bear": "280000",
            "dcf_bull": "400000"
        },
        "000250": {
            "insight": "아일리아 바이오시밀러 임상 성공 및 글로벌 시장 진출 기대감으로 투자 매력 상승.",
            "risk": "임상 결과에 따른 주가 변동성 확대 가능성이 존재함.",
            "swot_s": "바이오시밀러 개발 능력, 글로벌 시장 진출 가능성, 제약 산업 성장",
            "swot_w": "높은 연구 개발 비용, 임상 시험 성공 불확실성, 경쟁 심화",
            "swot_o": "고령화 사회 진입, 바이오시밀러 시장 확대, 정부의 바이오 산업 육성 정책",
            "swot_t": "임상 시험 실패 위험, 경쟁 심화, 규제 강화",
            "upside": "+30%",
            "dcf_target": "120000",
            "dcf_bear": "80000",
            "dcf_bull": "150000"
        },
        "277810": {
            "insight": "협동 로봇 시장 성장과 삼성전자의 투자 유치로 성장 잠재력 확대, 높은 밸류에이션은 부담.",
            "risk": "로봇 시장 경쟁 심화 및 높은 밸류에이션에 대한 부담이 존재함.",
            "swot_s": "협동 로봇 기술력, 삼성전자 투자 유치, 로봇 시장 성장",
            "swot_w": "높은 밸류에이션, 경쟁 심화, 제한적인 생산능력",
            "swot_o": "자동화 수요 증가, 스마트 팩토리 확산, 정부의 로봇 산업 육성 정책",
            "swot_t": "경쟁 심화 (두산로보틱스 등), 경기 침체, 기술 변화에 대한 대응",
            "upside": "+15%",
            "dcf_target": "250000",
            "dcf_bear": "180000",
            "dcf_bull": "300000"
        },
        "298380": {
            "insight": "이중항체 플랫폼 기술을 기반으로 한 파이프라인 확장이 기대됩니다.",
            "risk": "임상 개발 실패 및 경쟁 심화 가능성이 존재합니다.",
            "swot_s": "이중항체 플랫폼 기술, 파이프라인 확장, 기술이전 경험",
            "swot_w": "임상 개발 단계, 자금 조달 필요성, 경쟁사 대비 후발주자",
            "swot_o": "글로벌 제약사와의 협력 기회, 면역항암제 시장 성장, 정부 지원 정책",
            "swot_t": "임상 실패 위험, 경쟁 심화, 약가 인하 압력",
            "upside": "+20%",
            "dcf_target": "35000",
            "dcf_bear": "20000",
            "dcf_bull": "45000"
        },
        "950160": {
            "insight": "미국 FDA 임상 재개 여부에 따라 주가 변동성이 클 수 있습니다.",
            "risk": "임상 재개 불확실성 및 소송 리스크가 존재합니다.",
            "swot_s": "퇴행성관절염 세포 유전자 치료제 잠재력, 기술력, 글로벌 시장 진출 가능성",
            "swot_w": "임상 중단 이력, 자금 부족, 규제 리스크",
            "swot_o": "고령화 사회 진입, 퇴행성관절염 치료제 시장 성장, 혁신 치료 기술에 대한 관심 증가",
            "swot_t": "임상 실패 위험, 경쟁 심화, 법적 소송 결과",
            "upside": "+50%",
            "dcf_target": "10000",
            "dcf_bear": "1000",
            "dcf_bull": "20000"
        },
        "058470": {
            "insight": "반도체 테스트 소켓 시장의 성장과 함께 꾸준한 실적 성장이 예상됩니다.",
            "risk": "반도체 업황 변동에 따른 실적 영향이 있을 수 있습니다.",
            "swot_s": "반도체 테스트 소켓 시장 점유율, 기술 경쟁력, 안정적인 고객 기반",
            "swot_w": "특정 고객 의존도, 반도체 업황 변동에 민감, 제한적인 사업 다각화",
            "swot_o": "반도체 시장 성장, 고성능 반도체 수요 증가, 신규 고객 확보 기회",
            "swot_t": "반도체 경기 침체, 경쟁 심화, 기술 변화에 대한 대응",
            "upside": "+15%",
            "dcf_target": "250000",
            "dcf_bear": "180000",
            "dcf_bull": "300000"
        },
        "214370": {
            "insight": "글로벌 더마 코스메틱 시장 확대에 따른 수혜가 예상됩니다.",
            "risk": "경쟁 심화 및 중국 시장 의존도가 높다는 점이 리스크입니다.",
            "swot_s": "펩타이드 기술력, 글로벌 브랜드 인지도, 다수의 해외 판매 채널",
            "swot_w": "중국 시장 의존도, 높은 마케팅 비용, 경쟁 심화",
            "swot_o": "글로벌 더마 코스메틱 시장 성장, 온라인 판매 채널 확대, 신제품 출시 효과",
            "swot_t": "중국 경기 둔화, 경쟁 심화, 규제 변화",
            "upside": "+10%",
            "dcf_target": "80000",
            "dcf_bear": "60000",
            "dcf_bull": "90000"
        },
        "141080": {
            "insight": "ADC 플랫폼 기술을 바탕으로 한 기술 이전 및 파이프라인 확장 가능성이 높습니다.",
            "risk": "임상 개발 실패 및 경쟁 심화 가능성이 존재합니다.",
            "swot_s": "ADC 플랫폼 기술, 자체 개발 파이프라인, 기술 이전 경험",
            "swot_w": "임상 개발 단계, 자금 조달 필요성, 경쟁사 대비 후발주자",
            "swot_o": "ADC 치료제 시장 성장, 글로벌 제약사와의 협력 기회, 정부 지원 정책",
            "swot_t": "임상 실패 위험, 경쟁 심화, 약가 인하 압력",
            "upside": "+25%",
            "dcf_target": "60000",
            "dcf_bear": "35000",
            "dcf_bull": "75000"
        },
        "322000": {
            "insight": "태양광 발전 시장 성장과 함께 실적 개선이 기대됩니다.",
            "risk": "원자재 가격 변동 및 정부 정책 변화에 민감합니다.",
            "swot_s": "태양광 모듈 기술력, 브랜드 인지도, 국내외 시장 네트워크",
            "swot_w": "원자재 가격 변동에 민감, 정부 정책 의존도, 경쟁 심화",
            "swot_o": "글로벌 태양광 발전 시장 성장, 신재생에너지 투자 확대, 정부 지원 정책",
            "swot_t": "글로벌 경기 침체, 경쟁 심화, 정책 변화",
            "upside": "+15%",
            "dcf_target": "55000",
            "dcf_bear": "40000",
            "dcf_bull": "65000"
        },
        "054620": {
            "insight": "디스플레이 및 반도체 장비 시장 성장과 함께 수혜가 예상됩니다.",
            "risk": "디스플레이 및 반도체 투자 감소 시 실적에 부정적인 영향을 미칠 수 있습니다.",
            "swot_s": "디스플레이 및 반도체 장비 기술력, 오랜 업력, 안정적인 고객 기반",
            "swot_w": "특정 고객 의존도, 디스플레이 및 반도체 투자 변동에 민감, 사업 다각화 필요",
            "swot_o": "디스플레이 및 반도체 시장 성장, 신규 장비 수요 증가, 해외 시장 진출 기회",
            "swot_t": "디스플레이 및 반도체 투자 감소, 경쟁 심화, 기술 변화에 대한 대응",
            "upside": "+10%",
            "dcf_target": "20000",
            "dcf_bear": "15000",
            "dcf_bull": "25000"
        },
        "027360": {
            "insight": "벤처 투자 시장 활성화에 따른 투자 수익 증가가 기대됩니다.",
            "risk": "투자 실패 및 금리 인상에 따른 투자 심리 위축 가능성이 존재합니다.",
            "swot_s": "오랜 투자 경험, 투자 포트폴리오 다각화, 우수한 투자 인력",
            "swot_w": "투자 실패 위험, 금리 변동에 민감, 벤처 투자 시장 변동성",
            "swot_o": "벤처 투자 시장 성장, 유망 스타트업 등장, 정부 지원 정책",
            "swot_t": "금리 인상, 경기 침체, 투자 심리 위축",
            "upside": "+15%",
            "dcf_target": "5000",
            "dcf_bear": "3500",
            "dcf_bull": "6000"
        },
        "089230": {
            "insight": "엔터테인먼트 시장 성장과 함께 신규 콘텐츠 제작 및 유통 확대가 기대됩니다.",
            "risk": "콘텐츠 흥행 실패 및 경쟁 심화 가능성이 존재합니다.",
            "swot_s": "다양한 콘텐츠 제작 능력, 강력한 IP, 글로벌 유통망",
            "swot_w": "콘텐츠 흥행 의존도, 높은 제작 비용, 경쟁 심화",
            "swot_o": "글로벌 엔터테인먼트 시장 성장, OTT 플랫폼 확대, 신규 콘텐츠 수요 증가",
            "swot_t": "콘텐츠 흥행 실패, 경쟁 심화, 불법 복제",
            "upside": "+20%",
            "dcf_target": "3000",
            "dcf_bear": "2000",
            "dcf_bull": "4000"
        },
        "307750": {
            "insight": "원료의약품 시장 성장과 함께 CMO 사업 확장이 기대됩니다.",
            "risk": "제약 업황 변동 및 경쟁 심화 가능성이 존재합니다.",
            "swot_s": "원료의약품 생산 능력, CMO 사업 경쟁력, 안정적인 고객 기반",
            "swot_w": "제약 업황 변동에 민감, 경쟁 심화, 품질 관리 중요",
            "swot_o": "원료의약품 시장 성장, CMO 수요 증가, 해외 시장 진출 기회",
            "swot_t": "제약 경기 침체, 경쟁 심화, 규제 변화",
            "upside": "+10%",
            "dcf_target": "12000",
            "dcf_bear": "9000",
            "dcf_bull": "15000"
        },
        "043150": {
            "insight": "치과용 디지털 엑스레이 시장 성장과 함께 글로벌 시장 점유율 확대가 예상됩니다.",
            "risk": "경쟁 심화 및 기술 변화에 대한 대응이 필요합니다.",
            "swot_s": "치과용 디지털 엑스레이 기술력, 글로벌 브랜드 인지도, широкая сеть дистрибуции",
            "swot_w": "경쟁 심화, 기술 변화에 대한 대응, 특정 시장 의존도",
            "swot_o": "글로벌 치과용 디지털 엑스레이 시장 성장, 디지털 덴티스트리 트렌드 확산, 신흥 시장 성장",
            "swot_t": "경기 침체, 경쟁 심화, 기술 변화",
            "upside": "+15%",
            "dcf_target": "45000",
            "dcf_bear": "35000",
            "dcf_bull": "55000"
        },
        "229000": {
            "insight": "분자진단 기술을 기반으로 한 암 진단 시장 확대가 기대됩니다.",
            "risk": "기술 경쟁 심화 및 규제 변화에 민감합니다.",
            "swot_s": "분자진단 기술력, 암 진단 제품 포트폴리오, 연구 개발 능력",
            "swot_w": "경쟁 심화, 규제 변화에 민감, 자금 조달 필요성",
            "swot_o": "암 진단 시장 성장, 개인 맞춤형 의료 트렌드 확산, 정부 지원 정책",
            "swot_t": "기술 경쟁 심화, 규제 강화, 신제품 출시 지연",
            "upside": "+20%",
            "dcf_target": "18000",
            "dcf_bear": "12000",
            "dcf_bull": "22000"
        },
        "006920": {
            "insight": "콘크리트 혼화제 시장의 안정적인 성장과 함께 수익성 개선이 기대됩니다.",
            "risk": "건설 경기 침체 및 원자재 가격 변동에 민감합니다.",
            "swot_s": "콘크리트 혼화제 기술력, 오랜 업력, 안정적인 고객 기반",
            "swot_w": "건설 경기 변동에 민감, 원자재 가격 변동에 민감, 사업 다각화 필요",
            "swot_o": "건설 시장 성장, 친환경 콘크리트 수요 증가, 해외 시장 진출 기회",
            "swot_t": "건설 경기 침체, 원자재 가격 상승, 경쟁 심화",
            "upside": "+10%",
            "dcf_target": "8000",
            "dcf_bear": "6000",
            "dcf_bull": "9000"
        },
        "061040": {
            "insight": "미용 의료기기 시장 성장과 함께 신규 제품 출시 및 해외 시장 확대를 통한 성장 기대됩니다.",
            "risk": "경쟁 심화 및 의료기기 규제 강화에 민감합니다.",
            "swot_s": "미용 의료기기 기술력, 브랜드 인지도, 해외 판매 네트워크",
            "swot_w": "경쟁 심화, 의료기기 규제에 민감, 특정 제품 의존도",
            "swot_o": "미용 의료기기 시장 성장, 고령화 사회 진입, 해외 시장 확대 기회",
            "swot_t": "경쟁 심화, 규제 강화, 신제품 출시 지연",
            "upside": "+15%",
            "dcf_target": "15000",
            "dcf_bear": "11000",
            "dcf_bull": "18000"
        },
        "001020": {
            "insight": "제지 산업의 안정적인 수요 기반과 함께 친환경 포장재 시장 진출을 통한 성장 가능성이 있습니다.",
            "risk": "원자재 가격 변동 및 제지 산업 경쟁 심화에 민감합니다.",
            "swot_s": "제지 생산 능력, 오랜 업력, 안정적인 고객 기반",
            "swot_w": "원자재 가격 변동에 민감, 제지 산업 경쟁 심화, 환경 규제 강화",
            "swot_o": "친환경 포장재 시장 성장, 택배 시장 성장, 정부 지원 정책",
            "swot_t": "경기 침체, 원자재 가격 상승, 경쟁 심화",
            "upside": "+5%",
            "dcf_target": "3500",
            "dcf_bear": "2500",
            "dcf_bull": "4000"
        },
        "001510": {
            "insight": "금리 인상 사이클 종료 및 증시 활황 시 수혜 예상되나, 경쟁 심화 및 변동성이 리스크 요인.",
            "risk": "증시 변동성 확대 및 거래대금 감소 시 수익성 악화 가능성 존재.",
            "swot_s": "브로커리지 강점, IB 부문 성장 가능성",
            "swot_w": "자기자본 규모 열위, 경쟁 심화",
            "swot_o": "금리 인하 가능성, 증시 활황 기대",
            "swot_t": "규제 강화, 경쟁사 M&A",
            "upside": "+15%",
            "dcf_target": "1200",
            "dcf_bear": "800",
            "dcf_bull": "1500"
        },
        "011930": {
            "insight": "반도체 및 클린룸 설비 투자 확대에 따른 수혜 기대되나, 경기 침체 시 투자 감소 위험 상존.",
            "risk": "반도체 및 디스플레이 투자 감소 시 실적 악화 우려.",
            "swot_s": "클린룸 설비 기술력, 반도체 시장 성장",
            "swot_w": "높은 경기 변동성, 특정 고객 의존도",
            "swot_o": "반도체 투자 확대, 정부 정책 지원",
            "swot_t": "글로벌 경기 침체, 경쟁 심화",
            "upside": "+20%",
            "dcf_target": "6000",
            "dcf_bear": "4000",
            "dcf_bull": "7500"
        },
        "004060": {
            "insight": "패션 경기 회복 시 실적 개선 가능하나, 경쟁 심화 및 소비 침체 지속 시 어려움 예상.",
            "risk": "패션 트렌드 변화에 대한 대응 실패 시 재고 증가 및 수익성 악화.",
            "swot_s": "브랜드 인지도, 유통망 확보",
            "swot_w": "재무 구조 취약, 낮은 수익성",
            "swot_o": "패션 경기 회복, 온라인 시장 성장",
            "swot_t": "경쟁 심화, 소비 심리 위축",
            "upside": "+10%",
            "dcf_target": "350",
            "dcf_bear": "250",
            "dcf_bull": "400"
        },
        "006340": {
            "insight": "전력망 투자 확대 및 건설 경기 회복 시 수혜 예상되나, 원자재 가격 변동성이 리스크 요인.",
            "risk": "구리 가격 상승 및 건설 경기 침체 지속 시 수익성 악화 가능성.",
            "swot_s": "전선 기술력, 안정적인 수요 기반",
            "swot_w": "원자재 가격 변동성, 높은 부채비율",
            "swot_o": "전력망 투자 확대, 건설 경기 회복",
            "swot_t": "원자재 가격 상승, 경쟁 심화",
            "upside": "+18%",
            "dcf_target": "9000",
            "dcf_bear": "7000",
            "dcf_bull": "10500"
        },
        "038500": {
            "insight": "정부의 SOC 투자 확대 및 건설 경기 회복 시 수혜 예상되나, 시멘트 가격 인상 제한 및 경쟁 심화가 리스크 요인.",
            "risk": "시멘트 가격 인상 실패 및 건설 경기 침체 지속 시 수익성 악화.",
            "swot_s": "수직계열화, 안정적인 수요처 확보",
            "swot_w": "환경 규제 강화, 높은 에너지 비용",
            "swot_o": "SOC 투자 확대, 건설 경기 회복",
            "swot_t": "경쟁 심화, 환경 규제 강화",
            "upside": "+12%",
            "dcf_target": "6000",
            "dcf_bear": "5000",
            "dcf_bull": "6800"
        },
        "001290": {
            "insight": "핀테크 플랫폼과의 시너지 효과 기대되나, 증시 변동성 확대 및 경쟁 심화가 리스크 요인.",
            "risk": "핀테크 플랫폼과의 시너지 효과 미흡 시 성장 정체.",
            "swot_s": "핀테크 플랫폼 연계, 디지털 금융 경쟁력 강화",
            "swot_w": "브랜드 인지도 부족, 경쟁 심화",
            "swot_o": "디지털 금융 시장 성장, 핀테크 규제 완화",
            "swot_t": "증시 변동성 확대, 빅테크 기업 진출",
            "upside": "+14%",
            "dcf_target": "1800",
            "dcf_bear": "1400",
            "dcf_bull": "2100"
        },
        "900300": {
            "insight": "중국 소비 회복 시 수혜 예상되나, 중국 경제 성장 둔화 및 경쟁 심화가 리스크 요인.",
            "risk": "중국 경제 성장 둔화 및 한한령 재개 시 실적 악화 우려.",
            "swot_s": "중국 시장 진출, 유기농 화장품 트렌드 부합",
            "swot_w": "중국 시장 의존도, 브랜드 인지도 부족",
            "swot_o": "중국 소비 회복, 유기농 화장품 시장 성장",
            "swot_t": "중국 경제 성장 둔화, 경쟁 심화",
            "upside": "+25%",
            "dcf_target": "3000",
            "dcf_bear": "2000",
            "dcf_bull": "4000"
        },
        "227950": {
            "insight": "바이오 사업 확장 및 신규 사업 진출 기대되나, 재무 구조 불안정성이 리스크 요인.",
            "risk": "자금 조달 어려움 지속 시 신규 사업 추진 차질.",
            "swot_s": "신규 사업 추진, 바이오 사업 확장",
            "swot_w": "재무 구조 불안정, 낮은 수익성",
            "swot_o": "신규 시장 진출, 정부 지원 정책",
            "swot_t": "자금 조달 어려움, 경쟁 심화",
            "upside": "+10%",
            "dcf_target": "800",
            "dcf_bear": "500",
            "dcf_bull": "900"
        },
        "187660": {
            "insight": "광고 시장 성장 및 디지털 광고 확대 수혜 기대되나, 경쟁 심화 및 경기 변동성이 리스크 요인.",
            "risk": "광고 경기 침체 및 경쟁 심화 시 수익성 악화 가능성.",
            "swot_s": "디지털 광고 경쟁력, 데이터 분석 능력",
            "swot_w": "높은 경기 변동성, 경쟁 심화",
            "swot_o": "디지털 광고 시장 성장, AI 기술 발전",
            "swot_t": "경기 침체, 개인정보 보호 규제 강화",
            "upside": "+16%",
            "dcf_target": "15000",
            "dcf_bear": "12000",
            "dcf_bull": "17000"
        }
    }
}