{
    "date": "2026-04-15 05:36:50 KST",
    "market_indices": {
        "KOSPI": {
            "symbol": "KS11",
            "name": "코스피",
            "price": "6,140.48",
            "change": "+2.89%"
        },
        "KOSDAQ": {
            "symbol": "KQ11",
            "name": "코스닥",
            "price": "1,153.86",
            "change": "+2.85%"
        },
        "KOSPI200": {
            "symbol": "KS200",
            "name": "코스피 200",
            "price": "925.46",
            "change": "+3.17%"
        }
    },
    "commodities": [
        {
            "name": "원/달러 환율",
            "price": "1,473.24",
            "change": "+nan%"
        },
        {
            "name": "WTI 원유",
            "price": "91.67",
            "change": "+0.43%"
        },
        {
            "name": "국제 금",
            "price": "4,852.40",
            "change": "+0.57%"
        }
    ],
    "sector_heatmap": [
        {
            "sector": "반도체",
            "change": 4.032,
            "change_str": "+4.03%",
            "stocks": [
                {
                    "symbol": "005930",
                    "name": "삼성전자",
                    "change": "+3.63%"
                },
                {
                    "symbol": "000660",
                    "name": "SK하이닉스",
                    "change": "+4.85%"
                },
                {
                    "symbol": "042700",
                    "name": "한미반도체",
                    "change": "+3.52%"
                }
            ]
        },
        {
            "sector": "바이오",
            "change": 2.9575,
            "change_str": "+2.96%",
            "stocks": [
                {
                    "symbol": "207940",
                    "name": "삼성바이오로직스",
                    "change": "+3.39%"
                },
                {
                    "symbol": "068270",
                    "name": "셀트리온",
                    "change": "+1.71%"
                },
                {
                    "symbol": "000100",
                    "name": "유한양행",
                    "change": "+3.53%"
                }
            ]
        },
        {
            "sector": "IT/플랫폼",
            "change": 2.7075,
            "change_str": "+2.71%",
            "stocks": [
                {
                    "symbol": "035420",
                    "name": "NAVER",
                    "change": "+4.47%"
                },
                {
                    "symbol": "035720",
                    "name": "카카오",
                    "change": "+3.12%"
                },
                {
                    "symbol": "035810",
                    "name": "이지홀딩스",
                    "change": "+0.17%"
                }
            ]
        },
        {
            "sector": "자동차",
            "change": 2.2925,
            "change_str": "+2.29%",
            "stocks": [
                {
                    "symbol": "005380",
                    "name": "현대차",
                    "change": "+3.36%"
                },
                {
                    "symbol": "000270",
                    "name": "기아",
                    "change": "+2.08%"
                },
                {
                    "symbol": "012330",
                    "name": "현대모비스",
                    "change": "+2.59%"
                }
            ]
        },
        {
            "sector": "게임/엔터",
            "change": 1.9580000000000002,
            "change_str": "+1.96%",
            "stocks": [
                {
                    "symbol": "036570",
                    "name": "NC",
                    "change": "-1.41%"
                },
                {
                    "symbol": "259960",
                    "name": "크래프톤",
                    "change": "+1.88%"
                },
                {
                    "symbol": "352820",
                    "name": "하이브",
                    "change": "+4.07%"
                }
            ]
        },
        {
            "sector": "금융/지주",
            "change": 1.3359999999999999,
            "change_str": "+1.34%",
            "stocks": [
                {
                    "symbol": "105560",
                    "name": "KB금융",
                    "change": "+1.73%"
                },
                {
                    "symbol": "055550",
                    "name": "신한지주",
                    "change": "+1.32%"
                },
                {
                    "symbol": "086790",
                    "name": "하나금융지주",
                    "change": "+0.75%"
                }
            ]
        },
        {
            "sector": "조선/중공업",
            "change": 0.7766666666666667,
            "change_str": "+0.78%",
            "stocks": [
                {
                    "symbol": "329180",
                    "name": "HD현대중공업",
                    "change": "-0.21%"
                },
                {
                    "symbol": "010140",
                    "name": "삼성중공업",
                    "change": "+0.90%"
                },
                {
                    "symbol": "009540",
                    "name": "HD한국조선해양",
                    "change": "+1.64%"
                }
            ]
        },
        {
            "sector": "2차전지",
            "change": 0.7549999999999999,
            "change_str": "+0.75%",
            "stocks": [
                {
                    "symbol": "373220",
                    "name": "LG에너지솔루션",
                    "change": "+1.63%"
                },
                {
                    "symbol": "006400",
                    "name": "삼성SDI",
                    "change": "+0.32%"
                },
                {
                    "symbol": "247540",
                    "name": "에코프로비엠",
                    "change": "+2.63%"
                }
            ]
        },
        {
            "sector": "철강/금속",
            "change": 0.6025,
            "change_str": "+0.60%",
            "stocks": [
                {
                    "symbol": "005490",
                    "name": "POSCO홀딩스",
                    "change": "+1.52%"
                },
                {
                    "symbol": "004020",
                    "name": "현대제철",
                    "change": "+0.76%"
                },
                {
                    "symbol": "010130",
                    "name": "고려아연",
                    "change": "+0.49%"
                }
            ]
        },
        {
            "sector": "화학/에너지",
            "change": 0.45000000000000007,
            "change_str": "+0.45%",
            "stocks": [
                {
                    "symbol": "051910",
                    "name": "LG화학",
                    "change": "+3.95%"
                },
                {
                    "symbol": "096770",
                    "name": "SK이노베이션",
                    "change": "-0.58%"
                },
                {
                    "symbol": "010950",
                    "name": "S-Oil",
                    "change": "-2.02%"
                }
            ]
        }
    ],
    "ipo_news": [
        {
            "name": "IPO/증자 정보 업데이트 중",
            "status": "알림",
            "manager": "-",
            "price": "-",
            "date": "-"
        }
    ],
    "market_news": [
        {
            "title": "1분기 영업익 '40조' 전망에...상위 1% '초고수' SK하이닉스 다시 쓸어담았다 [마켓PRO]",
            "url": "https://news.google.com/rss/articles/CBMiT0FVX3lxTE82bXZqWG9pY2FHMDhkQmJNaFBhMF9qalF0ZVRZQUMwb2ZZZkhJd09Nc01ZSnZ2UWtaN0FlM1JmRVE2UWNXTzlKTlFrM3pGS0k?oc=5",
            "source": "v.daum.net",
            "date": "Wed, 15 Apr 2026 02:03:07 GMT"
        },
        {
            "title": "[증시 인사이트] 국내증시 동반 상승 마감…코스피 6000선 회복",
            "url": "https://news.google.com/rss/articles/CBMiU0FVX3lxTE5lYzc0U2I1UFlfT0pGMlhRVm5iaFRhUjVnbG1qeDdLZFAyaWR4c0YzZWVqTlZuMVpPMVUzWmFyVU5kTW5RaXdFMFhwM2tuR1B4MktV0gFYQVVfeXFMTVoyWkNoXzl6YkZ1YWZMV2luY0tnLUJBMi1yMkNjZVF4Qm45c05OOUJvOUg3YlZoaTJYUm9uVkQ1RVNxWFEtMUUybWZ5dGZyaUlJbW8tZkthbA?oc=5",
            "source": "SBS Biz",
            "date": "Tue, 14 Apr 2026 06:16:00 GMT"
        },
        {
            "title": "전쟁 타격 가장 컸던 국내 증시...6천피 탈환 가능할까",
            "url": "https://news.google.com/rss/articles/CBMiXkFVX3lxTE5TYUZKWU9PTEhNQ3dVMlRNMUFrXzd2aXpWSjh1dE9jRDdDSmRDMUJsQUJEMHhkV1FEaUVTMUMxWWlQUnlKUjA1eW1XNEpjenlIa015Y1Rqc1VUSnF4UXc?oc=5",
            "source": "YTN",
            "date": "Sun, 12 Apr 2026 06:28:00 GMT"
        },
        {
            "title": "중동전쟁 후 전세계 하락률 '톱' 국내 증시, 회복도 빠를까",
            "url": "https://news.google.com/rss/articles/CBMiW0FVX3lxTFAyRTJaVXBIS2YtT2F2Qlh6SDFuenlZQ3paZzZxbDRmYTlHZkUwWnN0VmtscFhPTjdhb0JFNU4tUmFtcE5NM3dHUjdCYzZ0QmNEZUFyZVJkeGdTZVHSAWBBVV95cUxOU01CU094eDQwOFR1M1VYR2w0M0tnbFZlTlRZeUFfLVFWQTBhMnRoLXhuQ0RGdDhJNEswMVZkTXVqM3FQb0d3a2ZNVFM4QndkMjctNTlHRXJuaXBfeF9pOWo?oc=5",
            "source": "연합뉴스",
            "date": "Sat, 11 Apr 2026 22:03:00 GMT"
        },
        {
            "title": "[ETF 400조 시대]3년만에 4배 커진 ETF 시장…대한민국 투자지도 바꿨다",
            "url": "https://news.google.com/rss/articles/CBMiT0FVX3lxTE0zeENJeS1kbExFZDdBeXNDOEdzbHdkZEp1M0lTRTE3SkgtYVBtQ0dFYi1kNGdvbmRILUFkVDRMRGM4ZU1sVS1RZEtGcjlIelU?oc=5",
            "source": "v.daum.net",
            "date": "Wed, 15 Apr 2026 00:32:36 GMT"
        },
        {
            "title": "[이 시각 시황] 美 양자컴 관련주 급등 마감…국내 관련주 상승세",
            "url": "https://news.google.com/rss/articles/CBMiT0FVX3lxTE9tU2xLZW9xSlhiZWgzSFpEVVJuenVLOEt1Mk1YbEVYaUJjWC1TWkpmT1FmRGNmb0xmRVRzVjgyYTVHX3o3d245aVIwME8zb28?oc=5",
            "source": "v.daum.net",
            "date": "Wed, 15 Apr 2026 00:37:12 GMT"
        },
        {
            "title": "\"오늘 6000피 간다\"...협상결렬에도 1조 베팅했던 개미들, 삼성·하이닉스 '강세'",
            "url": "https://news.google.com/rss/articles/CBMiT0FVX3lxTE15MDlfaUx3anE1V1JlaWprQ2tzM0dDU2NtNklEZzhHejlGNUNJWjl5QjBBWkQwTkFleVk4ZEh4RmVENlA2WVdjeEdndF9ndU0?oc=5",
            "source": "v.daum.net",
            "date": "Mon, 13 Apr 2026 23:43:31 GMT"
        },
        {
            "title": "SK하닉 '신고가' 썼는데…'상위 1%' 초고수들 팔아치운 이유 [마켓PRO]",
            "url": "https://news.google.com/rss/articles/CBMiRkFVX3lxTE1sOWYtTks2ejhhbXQ3THRZWk51ZG9Lc0NKVWUtYVl6RHFKWF90eEJvcFlfaDdqWkRNQ09IMTU2WmNMNlR1c2c?oc=5",
            "source": "v.daum.net",
            "date": "Tue, 14 Apr 2026 07:54:56 GMT"
        },
        {
            "title": "[뉴스특보] 협상 기대감에 증시 '들썩'…코스피, 6천선 돌파",
            "url": "https://news.google.com/rss/articles/CBMiRkFVX3lxTE5fc282QU5RMXZqdVJSYVlzRlU0YWFyZFFjMFV1ai1QMWxOaGJnd1luSmZaT1VMQjhjdTlrVGs1ZENyR1hlRlE?oc=5",
            "source": "v.daum.net",
            "date": "Tue, 14 Apr 2026 04:20:40 GMT"
        },
        {
            "title": "호르무즈 봉쇄에 프리마켓 약세…삼전·SK하닉·현대차·LG엔솔 ‘시총 빅4’ 동반 급락",
            "url": "https://news.google.com/rss/articles/CBMiRkFVX3lxTFBrbFRmZ091eGVDS2U5OVZzYlNKZnhNRktQUmlzZXBnUEI5ck50RzlKSV94ZzRWeWpTOFFFV0tzWGUwZ2NBUUE?oc=5",
            "source": "v.daum.net",
            "date": "Sun, 12 Apr 2026 23:24:02 GMT"
        }
    ],
    "investor_flows": {
        "KOSPI": [
            {
                "label": "개인",
                "value": "-9295억",
                "status": "매도"
            },
            {
                "label": "외국인",
                "value": "+6306억",
                "status": "매수"
            },
            {
                "label": "기관",
                "value": "-960억",
                "status": "매도"
            }
        ],
        "KOSDAQ": [
            {
                "label": "개인",
                "value": "-1618억",
                "status": "매도"
            },
            {
                "label": "외국인",
                "value": "+734억",
                "status": "매수"
            },
            {
                "label": "기관",
                "value": "+1277억",
                "status": "매수"
            }
        ]
    },
    "top_stocks": [
        {
            "rank": 1,
            "symbol": "009415",
            "name": "태영건설우",
            "price": "11,050",
            "change": "+30.00",
            "volume": "455,919",
            "market": "KOSPI"
        },
        {
            "rank": 2,
            "symbol": "203650",
            "name": "드림시큐리티",
            "price": "2,730",
            "change": "+30.00",
            "volume": "17,734,486",
            "market": "KOSDAQ"
        },
        {
            "rank": 3,
            "symbol": "066310",
            "name": "큐에스아이",
            "price": "17,510",
            "change": "+29.99",
            "volume": "4,986,281",
            "market": "KOSDAQ"
        },
        {
            "rank": 1,
            "symbol": "011930",
            "name": "신성이엔지",
            "price": "3,995",
            "change": "+6.82",
            "volume": "100,218,712",
            "market": "KOSPI"
        },
        {
            "rank": 2,
            "symbol": "047040",
            "name": "대우건설",
            "price": "28,800",
            "change": "+22.55",
            "volume": "80,915,867",
            "market": "KOSPI"
        },
        {
            "rank": 3,
            "symbol": "006340",
            "name": "대원전선",
            "price": "6,850",
            "change": "+24.32",
            "volume": "56,347,447",
            "market": "KOSPI"
        },
        {
            "rank": 1,
            "symbol": "005930",
            "name": "삼성전자",
            "price": "214,000",
            "change": "+3.63",
            "volume": "16,639,032",
            "market": "KOSPI"
        },
        {
            "rank": 2,
            "symbol": "000660",
            "name": "SK하이닉스",
            "price": "1,156,500",
            "change": "+4.85",
            "volume": "2,803,867",
            "market": "KOSPI"
        },
        {
            "rank": 1,
            "symbol": "086520",
            "name": "에코프로",
            "price": "149,000",
            "change": "+3.33",
            "volume": "941,771",
            "market": "KOSDAQ GLOBAL"
        },
        {
            "rank": 2,
            "symbol": "196170",
            "name": "알테오젠",
            "price": "375,000",
            "change": "+6.23",
            "volume": "269,338",
            "market": "KOSDAQ GLOBAL"
        }
    ],
    "leaders_kospi": [
        {
            "rank": 1,
            "symbol": "005930",
            "name": "삼성전자",
            "price": "214,000",
            "change": "+3.63",
            "volume": "16,639,032",
            "market": "KOSPI"
        },
        {
            "rank": 2,
            "symbol": "000660",
            "name": "SK하이닉스",
            "price": "1,156,500",
            "change": "+4.85",
            "volume": "2,803,867",
            "market": "KOSPI"
        },
        {
            "rank": 3,
            "symbol": "005935",
            "name": "삼성전자우",
            "price": "145,000",
            "change": "+2.55",
            "volume": "2,323,602",
            "market": "KOSPI"
        },
        {
            "rank": 4,
            "symbol": "005380",
            "name": "현대차",
            "price": "508,000",
            "change": "+3.36",
            "volume": "677,863",
            "market": "KOSPI"
        },
        {
            "rank": 5,
            "symbol": "373220",
            "name": "LG에너지솔루션",
            "price": "406,500",
            "change": "+1.63",
            "volume": "208,516",
            "market": "KOSPI"
        },
        {
            "rank": 6,
            "symbol": "402340",
            "name": "SK스퀘어",
            "price": "677,000",
            "change": "+5.78",
            "volume": "449,316",
            "market": "KOSPI"
        },
        {
            "rank": 7,
            "symbol": "012450",
            "name": "한화에어로스페이스",
            "price": "1,511,000",
            "change": "-0.79",
            "volume": "117,775",
            "market": "KOSPI"
        },
        {
            "rank": 8,
            "symbol": "207940",
            "name": "삼성바이오로직스",
            "price": "1,588,000",
            "change": "+3.39",
            "volume": "43,524",
            "market": "KOSPI"
        },
        {
            "rank": 9,
            "symbol": "034020",
            "name": "두산에너빌리티",
            "price": "104,500",
            "change": "+4.81",
            "volume": "4,673,974",
            "market": "KOSPI"
        },
        {
            "rank": 10,
            "symbol": "000270",
            "name": "기아",
            "price": "152,300",
            "change": "+2.08",
            "volume": "815,792",
            "market": "KOSPI"
        }
    ],
    "leaders_kosdaq": [
        {
            "rank": 1,
            "symbol": "086520",
            "name": "에코프로",
            "price": "149,000",
            "change": "+3.33",
            "volume": "941,771",
            "market": "KOSDAQ GLOBAL"
        },
        {
            "rank": 2,
            "symbol": "196170",
            "name": "알테오젠",
            "price": "375,000",
            "change": "+6.23",
            "volume": "269,338",
            "market": "KOSDAQ GLOBAL"
        },
        {
            "rank": 3,
            "symbol": "247540",
            "name": "에코프로비엠",
            "price": "203,000",
            "change": "+2.63",
            "volume": "271,913",
            "market": "KOSDAQ GLOBAL"
        },
        {
            "rank": 4,
            "symbol": "000250",
            "name": "삼천당제약",
            "price": "565,000",
            "change": "+8.65",
            "volume": "463,705",
            "market": "KOSDAQ"
        },
        {
            "rank": 5,
            "symbol": "277810",
            "name": "레인보우로보틱스",
            "price": "611,000",
            "change": "+1.33",
            "volume": "79,281",
            "market": "KOSDAQ"
        },
        {
            "rank": 6,
            "symbol": "298380",
            "name": "에이비엘바이오",
            "price": "164,600",
            "change": "+5.58",
            "volume": "337,472",
            "market": "KOSDAQ"
        },
        {
            "rank": 7,
            "symbol": "028300",
            "name": "HLB",
            "price": "67,950",
            "change": "+8.37",
            "volume": "1,518,601",
            "market": "KOSDAQ"
        },
        {
            "rank": 8,
            "symbol": "950160",
            "name": "코오롱티슈진",
            "price": "104,100",
            "change": "+9.01",
            "volume": "551,729",
            "market": "KOSDAQ"
        },
        {
            "rank": 9,
            "symbol": "058470",
            "name": "리노공업",
            "price": "112,300",
            "change": "+0.63",
            "volume": "666,451",
            "market": "KOSDAQ GLOBAL"
        },
        {
            "rank": 10,
            "symbol": "141080",
            "name": "리가켐바이오",
            "price": "192,400",
            "change": "+6.30",
            "volume": "488,275",
            "market": "KOSDAQ GLOBAL"
        }
    ],
    "gainers": [
        {
            "rank": 1,
            "symbol": "009415",
            "name": "태영건설우",
            "price": "11,050",
            "change": "+30.00",
            "volume": "455,919",
            "market": "KOSPI"
        },
        {
            "rank": 2,
            "symbol": "203650",
            "name": "드림시큐리티",
            "price": "2,730",
            "change": "+30.00",
            "volume": "17,734,486",
            "market": "KOSDAQ"
        },
        {
            "rank": 3,
            "symbol": "066310",
            "name": "큐에스아이",
            "price": "17,510",
            "change": "+29.99",
            "volume": "4,986,281",
            "market": "KOSDAQ"
        },
        {
            "rank": 4,
            "symbol": "017900",
            "name": "광전자",
            "price": "17,780",
            "change": "+29.97",
            "volume": "4,984,952",
            "market": "KOSPI"
        },
        {
            "rank": 5,
            "symbol": "123010",
            "name": "알엔티엑스",
            "price": "1,735",
            "change": "+29.96",
            "volume": "8,788,306",
            "market": "KOSDAQ"
        },
        {
            "rank": 6,
            "symbol": "294630",
            "name": "서남",
            "price": "5,530",
            "change": "+29.96",
            "volume": "8,446,608",
            "market": "KOSDAQ"
        },
        {
            "rank": 7,
            "symbol": "456010",
            "name": "아이씨티케이",
            "price": "22,950",
            "change": "+29.95",
            "volume": "2,896,111",
            "market": "KOSDAQ"
        },
        {
            "rank": 8,
            "symbol": "038060",
            "name": "루멘스",
            "price": "1,267",
            "change": "+29.95",
            "volume": "10,611,397",
            "market": "KOSDAQ"
        },
        {
            "rank": 9,
            "symbol": "184230",
            "name": "SGA솔루션즈",
            "price": "703",
            "change": "+29.94",
            "volume": "16,259,182",
            "market": "KOSDAQ"
        },
        {
            "rank": 10,
            "symbol": "131760",
            "name": "파인텍",
            "price": "829",
            "change": "+29.94",
            "volume": "14,379,957",
            "market": "KOSDAQ"
        }
    ],
    "volume": [
        {
            "rank": 1,
            "symbol": "011930",
            "name": "신성이엔지",
            "price": "3,995",
            "change": "+6.82",
            "volume": "100,218,712",
            "market": "KOSPI"
        },
        {
            "rank": 2,
            "symbol": "047040",
            "name": "대우건설",
            "price": "28,800",
            "change": "+22.55",
            "volume": "80,915,867",
            "market": "KOSPI"
        },
        {
            "rank": 3,
            "symbol": "006340",
            "name": "대원전선",
            "price": "6,850",
            "change": "+24.32",
            "volume": "56,347,447",
            "market": "KOSPI"
        },
        {
            "rank": 4,
            "symbol": "027040",
            "name": "서울전자통신",
            "price": "979",
            "change": "+29.67",
            "volume": "50,345,261",
            "market": "KOSDAQ"
        },
        {
            "rank": 5,
            "symbol": "001440",
            "name": "대한전선",
            "price": "41,550",
            "change": "+29.24",
            "volume": "35,131,190",
            "market": "KOSPI"
        },
        {
            "rank": 6,
            "symbol": "027360",
            "name": "아주IB투자",
            "price": "12,130",
            "change": "+7.06",
            "volume": "33,986,774",
            "market": "KOSDAQ"
        },
        {
            "rank": 7,
            "symbol": "005880",
            "name": "대한해운",
            "price": "2,685",
            "change": "+1.32",
            "volume": "32,518,347",
            "market": "KOSPI"
        },
        {
            "rank": 8,
            "symbol": "050890",
            "name": "쏠리드",
            "price": "18,440",
            "change": "+9.24",
            "volume": "32,116,562",
            "market": "KOSDAQ"
        },
        {
            "rank": 9,
            "symbol": "062970",
            "name": "한국첨단소재",
            "price": "4,125",
            "change": "+6.18",
            "volume": "31,211,529",
            "market": "KOSDAQ"
        },
        {
            "rank": 10,
            "symbol": "046970",
            "name": "우리로",
            "price": "14,450",
            "change": "+21.84",
            "volume": "30,285,348",
            "market": "KOSDAQ"
        }
    ],
    "ai_analysis": {}
}