{
    "date": "2026-04-14 08:59:29 KST",
    "market_indices": {
        "KOSPI": {
            "symbol": "KS11",
            "name": "코스피",
            "price": "5,967.75",
            "change": "+2.74%"
        },
        "KOSDAQ": {
            "symbol": "KQ11",
            "name": "코스닥",
            "price": "1,121.88",
            "change": "+2.00%"
        },
        "KOSPI200": {
            "symbol": "KS200",
            "name": "코스피 200",
            "price": "897.00",
            "change": "+3.01%"
        }
    },
    "commodities": [
        {
            "name": "원/달러 환율",
            "price": "1,473.02",
            "change": "+nan%"
        },
        {
            "name": "WTI 원유",
            "price": "96.76",
            "change": "-2.34%"
        },
        {
            "name": "국제 금",
            "price": "4,807.00",
            "change": "+1.36%"
        }
    ],
    "sector_heatmap": [
        {
            "sector": "자동차",
            "change": 2.63,
            "change_str": "+2.63%",
            "stocks": [
                {
                    "symbol": "005380",
                    "name": "현대차",
                    "change": "+2.72%"
                },
                {
                    "symbol": "000270",
                    "name": "기아",
                    "change": "+1.22%"
                },
                {
                    "symbol": "012330",
                    "name": "현대모비스",
                    "change": "+3.45%"
                }
            ]
        },
        {
            "sector": "반도체",
            "change": 2.4219999999999997,
            "change_str": "+2.42%",
            "stocks": [
                {
                    "symbol": "005930",
                    "name": "삼성전자",
                    "change": "+2.74%"
                },
                {
                    "symbol": "000660",
                    "name": "SK하이닉스",
                    "change": "+6.06%"
                },
                {
                    "symbol": "042700",
                    "name": "한미반도체",
                    "change": "+2.71%"
                }
            ]
        },
        {
            "sector": "조선/중공업",
            "change": 2.2033333333333336,
            "change_str": "+2.20%",
            "stocks": [
                {
                    "symbol": "329180",
                    "name": "HD현대중공업",
                    "change": "+3.46%"
                },
                {
                    "symbol": "010140",
                    "name": "삼성중공업",
                    "change": "+1.09%"
                },
                {
                    "symbol": "009540",
                    "name": "HD한국조선해양",
                    "change": "+2.06%"
                }
            ]
        },
        {
            "sector": "IT/플랫폼",
            "change": 1.8399999999999999,
            "change_str": "+1.84%",
            "stocks": [
                {
                    "symbol": "035420",
                    "name": "NAVER",
                    "change": "+1.26%"
                },
                {
                    "symbol": "035720",
                    "name": "카카오",
                    "change": "+2.34%"
                },
                {
                    "symbol": "035810",
                    "name": "이지홀딩스",
                    "change": "+1.20%"
                }
            ]
        },
        {
            "sector": "철강/금속",
            "change": 1.3924999999999998,
            "change_str": "+1.39%",
            "stocks": [
                {
                    "symbol": "005490",
                    "name": "POSCO홀딩스",
                    "change": "+0.42%"
                },
                {
                    "symbol": "004020",
                    "name": "현대제철",
                    "change": "+2.73%"
                },
                {
                    "symbol": "010130",
                    "name": "고려아연",
                    "change": "-0.84%"
                }
            ]
        },
        {
            "sector": "바이오",
            "change": 1.0125,
            "change_str": "+1.01%",
            "stocks": [
                {
                    "symbol": "207940",
                    "name": "삼성바이오로직스",
                    "change": "-0.90%"
                },
                {
                    "symbol": "068270",
                    "name": "셀트리온",
                    "change": "+2.00%"
                },
                {
                    "symbol": "000100",
                    "name": "유한양행",
                    "change": "+1.63%"
                }
            ]
        },
        {
            "sector": "게임/엔터",
            "change": 0.772,
            "change_str": "+0.77%",
            "stocks": [
                {
                    "symbol": "036570",
                    "name": "엔씨소프트",
                    "change": "+3.97%"
                },
                {
                    "symbol": "259960",
                    "name": "크래프톤",
                    "change": "-1.04%"
                },
                {
                    "symbol": "352820",
                    "name": "하이브",
                    "change": "-1.80%"
                }
            ]
        },
        {
            "sector": "금융/지주",
            "change": 0.466,
            "change_str": "+0.47%",
            "stocks": [
                {
                    "symbol": "105560",
                    "name": "KB금융",
                    "change": "-0.45%"
                },
                {
                    "symbol": "055550",
                    "name": "신한지주",
                    "change": "+0.00%"
                },
                {
                    "symbol": "086790",
                    "name": "하나금융지주",
                    "change": "+0.67%"
                }
            ]
        },
        {
            "sector": "화학/에너지",
            "change": -0.615,
            "change_str": "-0.61%",
            "stocks": [
                {
                    "symbol": "051910",
                    "name": "LG화학",
                    "change": "+0.44%"
                },
                {
                    "symbol": "096770",
                    "name": "SK이노베이션",
                    "change": "+0.08%"
                },
                {
                    "symbol": "010950",
                    "name": "S-Oil",
                    "change": "-2.38%"
                }
            ]
        },
        {
            "sector": "2차전지",
            "change": -1.7525,
            "change_str": "-1.75%",
            "stocks": [
                {
                    "symbol": "373220",
                    "name": "LG에너지솔루션",
                    "change": "-0.37%"
                },
                {
                    "symbol": "006400",
                    "name": "삼성SDI",
                    "change": "-1.47%"
                },
                {
                    "symbol": "247540",
                    "name": "에코프로비엠",
                    "change": "-0.60%"
                }
            ]
        }
    ],
    "ipo_news": [
        {
            "name": "에스바이오메딕스, 177억원 규모 제3자배정 ...",
            "status": "뉴스",
            "manager": "네이버금융",
            "price": "-",
            "date": "04.14",
            "full_title": "에스바이오메딕스, 177억원 규모 제3자배정 유상증자 결정",
            "url": "https://finance.naver.com/news/news_read.naver?article_id=0006257173&office_id=018&mode=LSS3D&type=0§ion_id=101§ion_id2=258§ion_id3=406&date=20260414&page=1"
        }
    ],
    "market_news": [
        {
            "title": "\"오늘 6000피 간다\"...협상결렬에도 1조 베팅했던 개미들, 삼성·하이닉스 '강세'",
            "url": "https://news.google.com/rss/articles/CBMiT0FVX3lxTE15MDlfaUx3anE1V1JlaWprQ2tzM0dDU2NtNklEZzhHejlGNUNJWjl5QjBBWkQwTkFleVk4ZEh4RmVENlA2WVdjeEdndF9ndU0?oc=5",
            "source": "v.daum.net",
            "date": "Mon, 13 Apr 2026 23:43:31 GMT"
        },
        {
            "title": "전쟁 타격 가장 컸던 국내 증시...6천피 탈환 가능할까",
            "url": "https://news.google.com/rss/articles/CBMiXkFVX3lxTE5TYUZKWU9PTEhNQ3dVMlRNMUFrXzd2aXpWSjh1dE9jRDdDSmRDMUJsQUJEMHhkV1FEaUVTMUMxWWlQUnlKUjA1eW1XNEpjenlIa015Y1Rqc1VUSnF4UXc?oc=5",
            "source": "YTN",
            "date": "Sun, 12 Apr 2026 06:28:00 GMT"
        },
        {
            "title": "상승 개장한 국내 증시",
            "url": "https://news.google.com/rss/articles/CBMiS0FVX3lxTE95cnNwVDhlNVByVVF2eFpWZzg5RkJpODlLSWdhWEVjOU44U0l6Qmg1UHdaSG5GZ0pMb0N3MkFUUlBvY25NR3U5WE1sSQ?oc=5",
            "source": "뉴스1",
            "date": "Tue, 14 Apr 2026 00:23:12 GMT"
        },
        {
            "title": "중동전쟁 후 전세계 하락률 '톱' 국내 증시, 회복도 빠를까",
            "url": "https://news.google.com/rss/articles/CBMiW0FVX3lxTFAyRTJaVXBIS2YtT2F2Qlh6SDFuenlZQ3paZzZxbDRmYTlHZkUwWnN0VmtscFhPTjdhb0JFNU4tUmFtcE5NM3dHUjdCYzZ0QmNEZUFyZVJkeGdTZVE?oc=5",
            "source": "연합뉴스",
            "date": "Sat, 11 Apr 2026 22:03:00 GMT"
        },
        {
            "title": "[증시 인사이트] 국내증시 혼조 마감…코스피 내리고 코스닥 오르고",
            "url": "https://news.google.com/rss/articles/CBMiU0FVX3lxTE5BVk1CY0Y0WGlTeU5wc2haNXZPRGFGczM4VzdoWnVfR1BQemh0TjhmaVljQWswam9aNUdMNkV0TnhVT1ZpUlpEN3c5NDhRWkpKVVBN0gFYQVVfeXFMTU5qcWZTZVMxRkZWUjczdDFUZzc2bFMwYVF0bkRyM240UDVKOUNhQm4tNzdPZHVvN3RFZTA4aUxMLUJwdkRwbmNSbUhCQmpZNWFrMk9Nd3F3ZA?oc=5",
            "source": "SBS Biz",
            "date": "Mon, 13 Apr 2026 09:58:00 GMT"
        },
        {
            "title": "‘TACO’ 내성 코스피, 6000 탈환…악재에도 버틴다",
            "url": "https://news.google.com/rss/articles/CBMiT0FVX3lxTE82am8zZEc2YlpIN085UVhpOU9kQnJCWWRwem55b1liWVUyajNhU2dRb29KcWx2RWt3VGdJb0Fac2xyLWU1YzZpdzMtazRzNGc?oc=5",
            "source": "v.daum.net",
            "date": "Tue, 14 Apr 2026 02:32:13 GMT"
        },
        {
            "title": "[뉴스특보] 협상 기대감에 증시 '들썩'…코스피, 6천선 돌파",
            "url": "https://news.google.com/rss/articles/CBMiT0FVX3lxTE9LOG8yRUg4SUo0bDJic0JLcFJEU2pTVzRQOUdxc0hfbzA5ZGdubE1zeE9lUGQ1T04xSlhDUDV6UlJBYVJ4RWxPYUVVSGM3MU0?oc=5",
            "source": "v.daum.net",
            "date": "Tue, 14 Apr 2026 04:20:40 GMT"
        },
        {
            "title": "\"저점매수 기회\"…외인들 삼전 팔고 하이닉스 담은 이유 [분석+]",
            "url": "https://news.google.com/rss/articles/CBMiT0FVX3lxTE1ScTF0RlRCNHJDd3Jid09yZ0YtcU0tVllmQ2Vtb29RNG5CbXM2ejVXRGdSTGpLQzdTd19yTjdNaDJXNDcwYTNHR0dTdnJTRVk?oc=5",
            "source": "v.daum.net",
            "date": "Mon, 13 Apr 2026 21:33:03 GMT"
        },
        {
            "title": "호르무즈 봉쇄에 프리마켓 약세…삼전·SK하닉·현대차·LG엔솔 ‘시총 빅4’ 동반 급락",
            "url": "https://news.google.com/rss/articles/CBMiRkFVX3lxTFBrbFRmZ091eGVDS2U5OVZzYlNKZnhNRktQUmlzZXBnUEI5ck50RzlKSV94ZzRWeWpTOFFFV0tzWGUwZ2NBUUE?oc=5",
            "source": "v.daum.net",
            "date": "Sun, 12 Apr 2026 23:24:02 GMT"
        },
        {
            "title": "예금 3조 늘 때 증시엔 70조 '폭주'…은행 아성 넘보는 증권사",
            "url": "https://news.google.com/rss/articles/CBMiT0FVX3lxTE9vQTJPRGtFMDhSUC0yRDludmtOZm5qZktkbm1SNGhpWWFnTzE4YXg2M3dCTmhhbDFLek1hYUtpZERhRTNrX3dNb3ZjWmtjb2s?oc=5",
            "source": "v.daum.net",
            "date": "Sun, 12 Apr 2026 08:46:05 GMT"
        }
    ],
    "investor_flows": {
        "KOSPI": [
            {
                "label": "개인",
                "value": "-23915억",
                "status": "매도"
            },
            {
                "label": "외국인",
                "value": "+8279억",
                "status": "매수"
            },
            {
                "label": "기관",
                "value": "+12542억",
                "status": "매수"
            }
        ],
        "KOSDAQ": [
            {
                "label": "개인",
                "value": "+1161억",
                "status": "매수"
            },
            {
                "label": "외국인",
                "value": "-63억",
                "status": "매도"
            },
            {
                "label": "기관",
                "value": "-1289억",
                "status": "매도"
            }
        ]
    },
    "top_stocks": [
        {
            "rank": 1,
            "symbol": "038060",
            "name": "루멘스",
            "price": "975",
            "change": "+30.00",
            "volume": "8,143,278",
            "market": "KOSDAQ"
        },
        {
            "rank": 2,
            "symbol": "368600",
            "name": "아이씨에이치",
            "price": "1,504",
            "change": "+29.99",
            "volume": "7,816,107",
            "market": "KOSDAQ"
        },
        {
            "rank": 3,
            "symbol": "432720",
            "name": "퀄리타스반도체",
            "price": "20,550",
            "change": "+29.98",
            "volume": "12,064,335",
            "market": "KOSDAQ"
        },
        {
            "rank": 1,
            "symbol": "008350",
            "name": "남선알미늄",
            "price": "3,080",
            "change": "+7.50",
            "volume": "146,968,693",
            "market": "KOSPI"
        },
        {
            "rank": 2,
            "symbol": "018470",
            "name": "조일알미늄",
            "price": "1,951",
            "change": "+1.77",
            "volume": "81,021,221",
            "market": "KOSPI"
        },
        {
            "rank": 3,
            "symbol": "010170",
            "name": "대한광통신",
            "price": "20,150",
            "change": "+1.41",
            "volume": "49,851,116",
            "market": "KOSDAQ"
        },
        {
            "rank": 1,
            "symbol": "005930",
            "name": "삼성전자",
            "price": "206,500",
            "change": "+2.74",
            "volume": "23,672,078",
            "market": "KOSPI"
        },
        {
            "rank": 2,
            "symbol": "000660",
            "name": "SK하이닉스",
            "price": "1,103,000",
            "change": "+6.06",
            "volume": "4,754,545",
            "market": "KOSPI"
        },
        {
            "rank": 1,
            "symbol": "086520",
            "name": "에코프로",
            "price": "144,200",
            "change": "+0.35",
            "volume": "597,615",
            "market": "KOSDAQ GLOBAL"
        },
        {
            "rank": 2,
            "symbol": "247540",
            "name": "에코프로비엠",
            "price": "197,800",
            "change": "-0.60",
            "volume": "306,781",
            "market": "KOSDAQ GLOBAL"
        }
    ],
    "leaders_kospi": [
        {
            "rank": 1,
            "symbol": "005930",
            "name": "삼성전자",
            "price": "206,500",
            "change": "+2.74",
            "volume": "23,672,078",
            "market": "KOSPI"
        },
        {
            "rank": 2,
            "symbol": "000660",
            "name": "SK하이닉스",
            "price": "1,103,000",
            "change": "+6.06",
            "volume": "4,754,545",
            "market": "KOSPI"
        },
        {
            "rank": 3,
            "symbol": "005935",
            "name": "삼성전자우",
            "price": "141,400",
            "change": "+2.09",
            "volume": "2,964,426",
            "market": "KOSPI"
        },
        {
            "rank": 4,
            "symbol": "005380",
            "name": "현대차",
            "price": "491,500",
            "change": "+2.72",
            "volume": "778,907",
            "market": "KOSPI"
        },
        {
            "rank": 5,
            "symbol": "373220",
            "name": "LG에너지솔루션",
            "price": "400,000",
            "change": "-0.37",
            "volume": "269,254",
            "market": "KOSPI"
        },
        {
            "rank": 6,
            "symbol": "402340",
            "name": "SK스퀘어",
            "price": "640,000",
            "change": "+10.34",
            "volume": "665,668",
            "market": "KOSPI"
        },
        {
            "rank": 7,
            "symbol": "012450",
            "name": "한화에어로스페이스",
            "price": "1,523,000",
            "change": "-0.46",
            "volume": "168,602",
            "market": "KOSPI"
        },
        {
            "rank": 8,
            "symbol": "207940",
            "name": "삼성바이오로직스",
            "price": "1,536,000",
            "change": "-0.90",
            "volume": "67,443",
            "market": "KOSPI"
        },
        {
            "rank": 9,
            "symbol": "034020",
            "name": "두산에너빌리티",
            "price": "99,700",
            "change": "+0.40",
            "volume": "1,937,143",
            "market": "KOSPI"
        },
        {
            "rank": 10,
            "symbol": "000270",
            "name": "기아",
            "price": "149,200",
            "change": "+1.22",
            "volume": "924,805",
            "market": "KOSPI"
        }
    ],
    "leaders_kosdaq": [
        {
            "rank": 1,
            "symbol": "086520",
            "name": "에코프로",
            "price": "144,200",
            "change": "+0.35",
            "volume": "597,615",
            "market": "KOSDAQ GLOBAL"
        },
        {
            "rank": 2,
            "symbol": "247540",
            "name": "에코프로비엠",
            "price": "197,800",
            "change": "-0.60",
            "volume": "306,781",
            "market": "KOSDAQ GLOBAL"
        },
        {
            "rank": 3,
            "symbol": "196170",
            "name": "알테오젠",
            "price": "353,000",
            "change": "-0.14",
            "volume": "170,578",
            "market": "KOSDAQ GLOBAL"
        },
        {
            "rank": 4,
            "symbol": "000250",
            "name": "삼천당제약",
            "price": "520,000",
            "change": "-1.14",
            "volume": "187,115",
            "market": "KOSDAQ"
        },
        {
            "rank": 5,
            "symbol": "277810",
            "name": "레인보우로보틱스",
            "price": "603,000",
            "change": "+2.90",
            "volume": "101,318",
            "market": "KOSDAQ"
        },
        {
            "rank": 6,
            "symbol": "298380",
            "name": "에이비엘바이오",
            "price": "155,900",
            "change": "+0.58",
            "volume": "318,448",
            "market": "KOSDAQ"
        },
        {
            "rank": 7,
            "symbol": "058470",
            "name": "리노공업",
            "price": "111,600",
            "change": "-1.59",
            "volume": "591,983",
            "market": "KOSDAQ GLOBAL"
        },
        {
            "rank": 8,
            "symbol": "028300",
            "name": "HLB",
            "price": "62,700",
            "change": "+7.55",
            "volume": "1,720,210",
            "market": "KOSDAQ"
        },
        {
            "rank": 9,
            "symbol": "950160",
            "name": "코오롱티슈진",
            "price": "95,500",
            "change": "+1.92",
            "volume": "284,537",
            "market": "KOSDAQ"
        },
        {
            "rank": 10,
            "symbol": "141080",
            "name": "리가켐바이오",
            "price": "181,000",
            "change": "-4.13",
            "volume": "536,857",
            "market": "KOSDAQ GLOBAL"
        }
    ],
    "gainers": [
        {
            "rank": 1,
            "symbol": "038060",
            "name": "루멘스",
            "price": "975",
            "change": "+30.00",
            "volume": "8,143,278",
            "market": "KOSDAQ"
        },
        {
            "rank": 2,
            "symbol": "368600",
            "name": "아이씨에이치",
            "price": "1,504",
            "change": "+29.99",
            "volume": "7,816,107",
            "market": "KOSDAQ"
        },
        {
            "rank": 3,
            "symbol": "432720",
            "name": "퀄리타스반도체",
            "price": "20,550",
            "change": "+29.98",
            "volume": "12,064,335",
            "market": "KOSDAQ"
        },
        {
            "rank": 4,
            "symbol": "078890",
            "name": "가온그룹",
            "price": "7,850",
            "change": "+29.97",
            "volume": "2,735,022",
            "market": "KOSDAQ"
        },
        {
            "rank": 5,
            "symbol": "035200",
            "name": "프럼파스트",
            "price": "4,900",
            "change": "+29.97",
            "volume": "2,342,377",
            "market": "KOSDAQ"
        },
        {
            "rank": 6,
            "symbol": "073540",
            "name": "에프알텍",
            "price": "6,440",
            "change": "+29.97",
            "volume": "6,366,476",
            "market": "KOSDAQ"
        },
        {
            "rank": 7,
            "symbol": "072950",
            "name": "빛샘전자",
            "price": "18,220",
            "change": "+29.96",
            "volume": "4,250,472",
            "market": "KOSDAQ"
        },
        {
            "rank": 8,
            "symbol": "027040",
            "name": "서울전자통신",
            "price": "755",
            "change": "+29.95",
            "volume": "1,772,569",
            "market": "KOSDAQ"
        },
        {
            "rank": 9,
            "symbol": "223310",
            "name": "사토시홀딩스",
            "price": "1,992",
            "change": "+29.94",
            "volume": "570,841",
            "market": "KOSDAQ"
        },
        {
            "rank": 10,
            "symbol": "027360",
            "name": "아주IB투자",
            "price": "11,330",
            "change": "+29.93",
            "volume": "32,018,687",
            "market": "KOSDAQ"
        }
    ],
    "volume": [
        {
            "rank": 1,
            "symbol": "008350",
            "name": "남선알미늄",
            "price": "3,080",
            "change": "+7.50",
            "volume": "146,968,693",
            "market": "KOSPI"
        },
        {
            "rank": 2,
            "symbol": "018470",
            "name": "조일알미늄",
            "price": "1,951",
            "change": "+1.77",
            "volume": "81,021,221",
            "market": "KOSPI"
        },
        {
            "rank": 3,
            "symbol": "010170",
            "name": "대한광통신",
            "price": "20,150",
            "change": "+1.41",
            "volume": "49,851,116",
            "market": "KOSDAQ"
        },
        {
            "rank": 4,
            "symbol": "014160",
            "name": "대영포장",
            "price": "1,336",
            "change": "+4.05",
            "volume": "48,542,988",
            "market": "KOSPI"
        },
        {
            "rank": 5,
            "symbol": "900300",
            "name": "오가닉티코스메틱",
            "price": "129",
            "change": "+3.20",
            "volume": "46,000,606",
            "market": "KOSDAQ"
        },
        {
            "rank": 6,
            "symbol": "046970",
            "name": "우리로",
            "price": "11,860",
            "change": "+18.72",
            "volume": "41,928,101",
            "market": "KOSDAQ"
        },
        {
            "rank": 7,
            "symbol": "069540",
            "name": "빛과전자",
            "price": "6,390",
            "change": "+29.88",
            "volume": "40,606,492",
            "market": "KOSDAQ"
        },
        {
            "rank": 8,
            "symbol": "340440",
            "name": "세림B&G",
            "price": "2,480",
            "change": "+7.36",
            "volume": "38,239,766",
            "market": "KOSDAQ"
        },
        {
            "rank": 9,
            "symbol": "005880",
            "name": "대한해운",
            "price": "2,650",
            "change": "-7.34",
            "volume": "38,225,183",
            "market": "KOSPI"
        },
        {
            "rank": 10,
            "symbol": "011930",
            "name": "신성이엔지",
            "price": "3,740",
            "change": "-4.71",
            "volume": "37,257,951",
            "market": "KOSPI"
        }
    ],
    "ai_analysis": {}
}